psb/__init__.py
psb/__main__.py
psb/conf.py
psb/display.py
psb/main.py
tests/__init__.py
tests/test_conf.py
tests/test_display.py
psb-0.17.0.dist-info/LICENSE
psb-0.17.0.dist-info/METADATA
psb-0.17.0.dist-info/WHEEL
psb-0.17.0.dist-info/entry_points.txt
psb-0.17.0.dist-info/top_level.txt
psb-0.17.0.dist-info/RECORD
